docs/__init__.py
docs/conf.py
stackinabox/__init__.py
stackinabox/stack.py
stackinabox/services/__init__.py
stackinabox/services/exceptions.py
stackinabox/services/router.py
stackinabox/services/service.py
stackinabox/util/__init__.py
stackinabox/util/deprecator.py
stackinabox/util/httpretty/__init__.py
stackinabox/util/httpretty/core.py
stackinabox/util/httpretty/decorator.py
stackinabox/util/requests_mock/__init__.py
stackinabox/util/requests_mock/core.py
stackinabox/util/requests_mock/decorator.py
stackinabox/util/requests_mock/reqcallable.py
stackinabox/util/responses/__init__.py
stackinabox/util/responses/core.py
stackinabox/util/responses/decorator.py
stackinabox/util/respx/__init__.py
stackinabox/util/respx/core.py
stackinabox/util/respx/decorator.py
stackinabox/util/tools/__init__.py
stackinabox/util/tools/caseinsensitivedict.py
stackinabox-0.14.dist-info/licenses/AUTHORS
stackinabox-0.14.dist-info/licenses/LICENSE
stackinabox-0.14.dist-info/METADATA
stackinabox-0.14.dist-info/WHEEL
stackinabox-0.14.dist-info/top_level.txt
stackinabox-0.14.dist-info/zip-safe
stackinabox-0.14.dist-info/RECORD
