Metadata-Version: 2.4
Name: stackinabox
Version: 0.14
Summary: RESTful API Testing Suite
Home-page: https://github.com/TestInABox/stackInABox
Author: Benjamen R. Meyer
Author-email: bm_witness@yahoo.com
License: Apache License 2.0
Classifier: Intended Audience :: Developers
Classifier: License :: OSI Approved :: Apache Software License
Classifier: Topic :: Software Development :: Testing
License-File: LICENSE
License-File: AUTHORS
Requires-Dist: six
Provides-Extra: httpretty
Requires-Dist: httpretty==1.1.4; extra == "httpretty"
Provides-Extra: requests-mock
Requires-Dist: requests-mock; extra == "requests-mock"
Provides-Extra: responses
Requires-Dist: responses>=0.4.0; extra == "responses"
Dynamic: license-file
